CHANGELOG.md
README.md
ophidian/__init__.py
ophidian/di_container.py
ophidian-0.2.0.dist-info/LICENSE
ophidian-0.2.0.dist-info/METADATA
ophidian-0.2.0.dist-info/WHEEL
ophidian-0.2.0.dist-info/RECORD
