Metadata-Version: 2.1
Name: ophidian
Version: 0.2.0
Summary: A dependency injection container for Python
Home-page: https://github.com/guardicode/ophidian
License: GPLv3
Author: Mike Salvatore
Author-email: mike.s.salvatore@gmail.com
Requires-Python: >=3.11,<4.0
Classifier: License :: OSI Approved :: GNU General Public License v3 (GPLv3)
Classifier: License :: Other/Proprietary License
Classifier: Programming Language :: Python :: 3
Classifier: Programming Language :: Python :: 3.11
Project-URL: Repository, https://github.com/guardicode/ophidian
